[
    {
        "up": [
            [
                0.7451182726159576,
                -4.0,
                2.008974344320221,
                -4.0,
                4.0,
                -4.0,
                0.7418545974183064,
                -4.0,
                2.0910863356045803
            ],
            [
                -4.0,
                -0.17926653920296653,
                2.5483282052778184,
                -3.719879785540985,
                -1.7421623065007872,
                3.287324362374976,
                -4.0,
                -0.5375721429695336,
                2.8562847686238886
            ]
        ],
        "pi": [
            [
                0.7573544111605534,
                0.7806876322348968,
                -0.721331619981859
            ],
            [
                0.6413662736313696,
                -0.46626800805563984,
                0.21270305073681509
            ]
        ],
        "ip": [
            [
                0.04403516545327629,
                0.0547664342604157
            ],
            [
                -0.0010560173673817236,
                0.32468236731175004
            ],
            [
                0.40660483723703617,
                -0.06405835950755574
            ]
        ],
        "down": [
            [
                -0.7573544111605534,
                -0.7806876322348968,
                0.721331619981859
            ],
            [
                -0.6413662736313696,
                0.46626800805563984,
                -0.21270305073681509
            ]
        ]
    },
    {
        "up": [
            [
                0.04680765715830522,
                0.05874087509905334
            ],
            [
                0.0025899354964189535,
                0.35005348655679136
            ],
            [
                0.4449538137332887,
                -0.0668143611946967
            ]
        ]
    }
]