[
    {
        "up": [
            [
                NaN,
                0.6396499778064302,
                -0.6702012940809067,
                -0.01745204679851481,
                NaN,
                NaN
            ],
            [
                NaN,
                NaN,
                NaN,
                NaN,
                -0.5596535653302614,
                -0.799797506840034
            ],
            [
                0.5492929280222176,
                -0.08437338682306447,
                NaN,
                -0.6182308545665933,
                NaN,
                NaN
            ],
            [
                NaN,
                NaN,
                NaN,
                NaN,
                NaN,
                NaN
            ],
            [
                NaN,
                NaN,
                NaN,
                NaN,
                0.057677246693117745,
                NaN
            ],
            [
                0.4293412228368699,
                0.2082965965554245,
                NaN,
                NaN,
                NaN,
                -0.3480536578178084
            ],
            [
                NaN,
                0.8987929068156196,
                -0.8644433367256987,
                NaN,
                -0.018941970950188576,
                -0.926409997551784
            ],
            [
                -0.08445266369299184,
                NaN,
                -0.18483604389323977,
                0.3744931893101577,
                -0.3461495896673501,
                NaN
            ],
            [
                NaN,
                NaN,
                NaN,
                NaN,
                -0.06950606431400316,
                NaN
            ]
        ],
        "pi": [
            [
                0.006599208554284447,
                -0.8072260078059289,
                NaN
            ],
            [
                NaN,
                NaN,
                -1.5070410197548512e-15
            ],
            [
                -0.007757376397385558,
                -0.006787270013597531,
                NaN
            ],
            [
                NaN,
                NaN,
                NaN
            ],
            [
                0.016929249651887607,
                0.014812145579735014,
                NaN
            ]
        ],
        "ip": [
            [
                -0.05690171000036059,
                NaN,
                NaN,
                -0.010025754106296123,
                -0.005425775462666437,
                NaN
            ],
            [
                0.00183215708728418,
                NaN,
                0.029868030848885594,
                0.24709457913739236,
                NaN,
                -0.03458182952810994
            ]
        ],
        "down": [
            [
                NaN,
                -0.44780331670332996,
                -0.034945646560606905
            ],
            [
                0.8773552681821265,
                NaN,
                NaN
            ],
            [
                NaN,
                NaN,
                NaN
            ],
            [
                NaN,
                NaN,
                -0.007008904233294505
            ],
            [
                NaN,
                -0.12462111838855636,
                0.6584434305575282
            ],
            [
                NaN,
                NaN,
                0.016012908982679548
            ],
            [
                NaN,
                -0.011127642314249196,
                -0.7176399635972195
            ]
        ]
    },
    {
        "up": [
            [
                NaN,
                -0.38164146439792873,
                0.22722551166573113,
                NaN,
                NaN,
                NaN
            ],
            [
                NaN,
                -0.27624199495918855,
                NaN,
                0.9588909001644103,
                -0.548398224836933,
                NaN
            ],
            [
                NaN,
                NaN,
                NaN,
                -0.3302078292258202,
                NaN,
                NaN
            ]
        ]
    }
]