[
    {
        "up": [
            [
                0.7862125186868246,
                -0.7914927169100678,
                -0.8382175196701669,
                0.491242156718829,
                -0.932260095240486,
                -0.8708568071559656
            ],
            [
                NaN,
                0.32349356124715367,
                0.7455533573177164,
                0.11844109784930665,
                NaN,
                NaN
            ],
            [
                -0.9831176465638333,
                NaN,
                NaN,
                0.1314450773338655,
                0.6513470219490844,
                -0.5567322935601042
            ],
            [
                0.0358740274518576,
                0.48291376592245683,
                0.9403242662109823,
                -0.02569949726161907,
                0.08087925457166498,
                -0.05699889208136376
            ],
            [
                0.3397467400308744,
                NaN,
                -0.032753914955157074,
                -0.6847604436832353,
                -0.8344802569402111,
                -0.0521763344995119
            ],
            [
                -0.26545522566562196,
                0.5612412956171643,
                -0.2618044001358506,
                -0.803420870542788,
                -0.41286461159988597,
                -0.682359973550885
            ],
            [
                0.06643118621571381,
                NaN,
                NaN,
                -0.04514391832019064,
                0.9885690608216648,
                -0.5570232804956934
            ],
            [
                NaN,
                0.817422666691431,
                0.5116657094657939,
                0.08135432461061787,
                0.5242941336277938,
                0.34244438680927897
            ],
            [
                -0.749827095996348,
                0.11800330357192526,
                0.91742684801471,
                0.661734641600348,
                -0.6575268765317104,
                0.24151461833966034
            ],
            [
                NaN,
                0.6127452733454086,
                NaN,
                0.49299636615534376,
                -0.5301682113445705,
                NaN
            ]
        ],
        "pi": [
            [
                0.13548275704814583,
                0.24600108057957187,
                0.5690841381130701
            ],
            [
                0.06717597403123371,
                0.08743887165551678,
                0.16890236956301868
            ],
            [
                NaN,
                NaN,
                2.7403072087239835
            ],
            [
                NaN,
                -1.2292500067395573,
                NaN
            ],
            [
                0.7324452207749313,
                0.6487549159473781,
                0.4219088553216138
            ],
            [
                NaN,
                NaN,
                NaN
            ],
            [
                0.10594990529762187,
                NaN,
                0.4497665346067782
            ],
            [
                0.09232971061436152,
                0.20551945888007667,
                1.9413216805671814
            ],
            [
                -0.03651583768201254,
                -0.019091650123624494,
                -0.005619677728174559
            ]
        ],
        "ip": [
            [
                NaN,
                NaN,
                NaN,
                -0.1619804205482106,
                0.3288042486629126,
                NaN,
                0.34719631624285285,
                0.024304695694888235,
                NaN
            ],
            [
                NaN,
                0.2090313685454271,
                0.035621968668323435,
                -0.3318875538591095,
                0.18648991677136958,
                NaN,
                -0.18126919754106985,
                -0.24773242222321695,
                0.06073147337640576
            ],
            [
                -0.42202815588972376,
                1.1681513779488026,
                -0.266904000485147,
                NaN,
                NaN,
                NaN,
                -0.25495243408857693,
                -1.1453086515630377,
                NaN
            ]
        ],
        "down": [
            [
                -0.07977696744638774,
                NaN,
                -0.2818795672000698
            ],
            [
                -0.9675523979837866,
                -0.2757457255192819,
                NaN
            ],
            [
                0.7238903313783187,
                0.2218840478065715,
                NaN
            ],
            [
                -0.967373381148775,
                -0.5505854289659005,
                NaN
            ],
            [
                NaN,
                -0.49559825394966933,
                -0.650087438532293
            ],
            [
                -0.4670756702404768,
                0.8729343760936428,
                -0.9531387704320475
            ],
            [
                -0.7511144924048416,
                NaN,
                -0.16428624177488374
            ],
            [
                NaN,
                NaN,
                -0.5506564398122165
            ],
            [
                0.11925979422687474,
                -0.10683809555410949,
                NaN
            ],
            [
                NaN,
                -0.20247833696294387,
                -0.9937878113544604
            ]
        ]
    },
    {
        "up": [
            [
                -0.4034928115247107,
                0.3580926928297801,
                0.5735466616010274,
                -0.10686908993751826,
                0.021295472663582747,
                0.8275196066622614,
                NaN,
                -0.30702614615660173,
                NaN
            ],
            [
                0.24511818810699343,
                0.27033375216799665,
                NaN,
                -0.4957126496930717,
                0.346473061337128,
                NaN,
                -0.37116063638040697,
                -0.39250048393333176,
                NaN
            ],
            [
                NaN,
                0.955917658833621,
                NaN,
                -0.6254694808315513,
                -0.08801948135754942,
                0.9506631187240713,
                -0.7085723713770505,
                -0.9052786923977927,
                NaN
            ]
        ]
    }
]